{"per_task":[{"attempts":{"breaker_attempts":200,"meta_cases":0},"audit_ok":true,"breaker_kpi":{"CDR":0.0,"NOVN":0.0,"TMR":200.0,"WFHR":0.0,"budget":{"attempt_budget":200},"canonicalization":"orjson_sort_keys_utf8","hash_algorithm":"blake3","hash_inputs":["schema_version","canonicalization","hash_algorithm","CDR","TMR","NOVN","WFHR","window","budget"],"schema_version":"v1","window":{"attempts":200}},"forge_decision":{"decision":"ADMIT","program_hash":"6c9e28085759935ff0478423176a270af7a1c0a9bcd176b99660bab276527d13","reason":"passes"},"program_hash":"6c9e28085759935ff0478423176a270af7a1c0a9bcd176b99660bab276527d13","task_id":"pyfunc_01","verdict":"PASS","warm_start_candidate_hash":"","warm_start_candidate_rejected":false,"warm_start_provided":false,"warm_start_store":false},{"attempts":{"breaker_attempts":1,"meta_cases":2},"audit_ok":true,"breaker_kpi":{"CDR":1.0,"NOVN":1.0,"TMR":1.0,"WFHR":0.0,"budget":{"attempt_budget":200},"canonicalization":"orjson_sort_keys_utf8","hash_algorithm":"blake3","hash_inputs":["schema_version","canonicalization","hash_algorithm","CDR","TMR","NOVN","WFHR","window","budget"],"schema_version":"v1","window":{"attempts":1}},"forge_decision":{"decision":"ADMIT","program_hash":"4ef159cd7e07b2993445e0922cc95dcdb430d2d0f288e053ba2ca7033592b749","reason":"passes"},"program_hash":"4ef159cd7e07b2993445e0922cc95dcdb430d2d0f288e053ba2ca7033592b749","task_id":"codepatch_pass_01","verdict":"PASS","warm_start_candidate_hash":"","warm_start_candidate_rejected":false,"warm_start_provided":false,"warm_start_store":false},{"attempts":{"breaker_attempts":200,"meta_cases":4},"audit_ok":true,"breaker_kpi":{"CDR":0.0,"NOVN":0.0,"TMR":200.0,"WFHR":0.0,"budget":{"attempt_budget":200},"canonicalization":"orjson_sort_keys_utf8","hash_algorithm":"blake3","hash_inputs":["schema_version","canonicalization","hash_algorithm","CDR","TMR","NOVN","WFHR","window","budget"],"schema_version":"v1","window":{"attempts":200}},"forge_decision":{"decision":"ADMIT","program_hash":"e6442dcaa6ac1532d3b7e7b5ba15aab4bbd8ec1c021a06cc1f90f0fd01316b0d","reason":"passes"},"program_hash":"e6442dcaa6ac1532d3b7e7b5ba15aab4bbd8ec1c021a06cc1f90f0fd01316b0d","task_id":"jsonspec_pass_01","verdict":"PASS","warm_start_candidate_hash":"","warm_start_candidate_rejected":false,"warm_start_provided":false,"warm_start_store":false}],"policy_version":"v1","store_updates":[{"program_hash":"6c9e28085759935ff0478423176a270af7a1c0a9bcd176b99660bab276527d13","store_path":"store/pyfunc/6c9e28085759935ff0478423176a270af7a1c0a9bcd176b99660bab276527d13.py"},{"program_hash":"4ef159cd7e07b2993445e0922cc95dcdb430d2d0f288e053ba2ca7033592b749","store_path":"store/codepatch/4ef159cd7e07b2993445e0922cc95dcdb430d2d0f288e053ba2ca7033592b749.patch"},{"program_hash":"e6442dcaa6ac1532d3b7e7b5ba15aab4bbd8ec1c021a06cc1f90f0fd01316b0d","store_path":"store/jsonspec/e6442dcaa6ac1532d3b7e7b5ba15aab4bbd8ec1c021a06cc1f90f0fd01316b0d.json"}],"suite_id":"suite_v8","totals":{"audit_failures":0,"breaker_attempts":401,"fail":0,"pass":3}}
